BayCatEncoder/__init__.py
BayCatEncoder/code.py
hierarchical_bay_cat_encoder-0.4.5.dist-info/LICENSE
hierarchical_bay_cat_encoder-0.4.5.dist-info/METADATA
hierarchical_bay_cat_encoder-0.4.5.dist-info/WHEEL
hierarchical_bay_cat_encoder-0.4.5.dist-info/top_level.txt
hierarchical_bay_cat_encoder-0.4.5.dist-info/RECORD
