Metadata-Version: 2.1
Name: hierarchical-bay-cat-encoder
Version: 0.4.5
Summary: Bayesian target encoder with the capacity to encode classes derived from categorical features that relate to one another in a hierarchical structure.
Home-page: https://github.com/libinruan/hierarchical_bayesian_target_encoder
Author: Li-Pin Juan
Author-email: lipin.juan02@gmail.com
License: UNKNOWN
Keywords: target encoder,bayesian,bayes,categorical features,hierarchical
Platform: UNKNOWN
Classifier: Programming Language :: Python :: 3
Classifier: License :: OSI Approved :: MIT License
Classifier: Operating System :: OS Independent
Requires-Python: >=3.6
